pyks/__init__.py
pyks/_nbdev.py
pyks/ks.py
pyks/ks2.py
pyks-1.1.5.dist-info/LICENSE
pyks-1.1.5.dist-info/LICENSE.md
pyks-1.1.5.dist-info/METADATA
pyks-1.1.5.dist-info/WHEEL
pyks-1.1.5.dist-info/top_level.txt
pyks-1.1.5.dist-info/RECORD
