Metadata-Version: 2.1
Name: pyks
Version: 1.1.5
Summary: Calculate KS statistic for models
Home-page: https://github.com/JiaxiangBU/pyks
Author: Jiaxiang Li
Author-email: alex.lijiaxiang@foxmail.com
License: MIT
Platform: UNKNOWN
Classifier: Programming Language :: Python :: 3
Classifier: License :: OSI Approved :: MIT License
Classifier: Operating System :: OS Independent
